maoproxy/__init__.py
maoproxy/proxy.py
maoproxy-0.0.1.dist-info/LICENSE
maoproxy-0.0.1.dist-info/METADATA
maoproxy-0.0.1.dist-info/WHEEL
maoproxy-0.0.1.dist-info/top_level.txt
maoproxy-0.0.1.dist-info/RECORD
