Metadata-Version: 2.1
Name: maoproxy
Version: 0.0.1
Summary: Free proxy list for python!
Home-page: https://github.com/mao2116
Author: mao2116
Author-email: mao2116@yandex.com
License: MIT
Keywords: mao2116,mao-hacking,mao-community,proxy list,free proxy,termux - command,termux,android hacking,mao tool,mao,pip proxy,python proxy,proxy list with python
Classifier: Development Status :: 4 - Beta
Classifier: Intended Audience :: Developers
Classifier: Topic :: Software Development :: Libraries :: Python Modules
Classifier: License :: OSI Approved :: MIT License
Classifier: Programming Language :: Python :: 3
Classifier: Operating System :: OS Independent
Classifier: Environment :: Console
Requires-Python: >=3.9.5
License-File: LICENSE
Requires-Dist: requests
